generate_mac/__init__.py
python_generate_mac-1.3.1.dist-info/LICENSE
python_generate_mac-1.3.1.dist-info/METADATA
python_generate_mac-1.3.1.dist-info/WHEEL
python_generate_mac-1.3.1.dist-info/top_level.txt
python_generate_mac-1.3.1.dist-info/RECORD
