Metadata-Version: 2.1
Name: python-generate-mac
Version: 1.3.1
Summary: Library for generating Ethernet MAC addresses
Home-page: https://github.com/GIJack/python-generate_mac
Author: GI_Jack
Author-email: GI_Jack@hackermail.com
License: UNKNOWN
Platform: UNKNOWN
Classifier: Programming Language :: Python :: 3
Classifier: License :: OSI Approved :: GNU General Public License v3 (GPLv3)
Classifier: Operating System :: OS Independent
Requires-Python: >=3.4
